stax_cx_automation_sdk/__init__.py
stax_cx_automation_sdk/api.py
stax_cx_automation_sdk/db.py
stax_cx_automation_sdk/helpers.py
stax_cx_automation_sdk/wrapper.py
stax_cx_automation_sdk/expressions/__init__.py
stax_cx_automation_sdk/expressions/context.py
stax_cx_automation_sdk/expressions/evaluate.py
stax_cx_automation_sdk/expressions/js.py
stax_cx_automation_sdk/expressions/types.py
stax_cx_automation_sdk/subprocess/__init__.py
stax_cx_automation_sdk/subprocess/run_code.py
stax_cx_automation_sdk-0.1.15.dist-info/METADATA
stax_cx_automation_sdk-0.1.15.dist-info/WHEEL
stax_cx_automation_sdk-0.1.15.dist-info/top_level.txt
stax_cx_automation_sdk-0.1.15.dist-info/RECORD
