Metadata-Version: 2.4
Name: stax_cx_automation_sdk
Version: 0.1.15
Summary: Stax.ai CX Automation SDK
Home-page: https://github.com/stax-ai/cx-automation-sdk
Author: Stax.ai, Inc. <https://stax.ai>
Author-email: developers@stax.ai
License: Proprietary
Classifier: Programming Language :: Python :: 3
Classifier: Operating System :: OS Independent
Requires-Python: >=3.6
Requires-Dist: retry_requests
Requires-Dist: functions_framework
Requires-Dist: js2py
Requires-Dist: pymongo
Dynamic: author
Dynamic: author-email
Dynamic: classifier
Dynamic: description
Dynamic: description-content-type
Dynamic: home-page
Dynamic: license
Dynamic: requires-dist
Dynamic: requires-python
Dynamic: summary
